wrdz/__init__.py
wrdz/base.py
wrdz/bit_io.py
wrdz/train.py
wrdz/dicts/en_US.dict
wrdz/dicts/urls.dict
wrdz-0.1.1.dist-info/METADATA
wrdz-0.1.1.dist-info/WHEEL
wrdz-0.1.1.dist-info/RECORD
