Metadata-Version: 2.4
Name: wrdz
Version: 0.1.1
Summary: Dictionary-based text compression optimized for short strings and URLs
Project-URL: Homepage, https://github.com/pjwerneck/wrdz
Project-URL: Bug Tracker, https://github.com/pjwerneck/wrdz/issues
Author-email: Pedro Werneck <pjwerneck@gmail.com>
Classifier: License :: OSI Approved :: MIT License
Classifier: Operating System :: OS Independent
Classifier: Programming Language :: Python :: 3
Classifier: Programming Language :: Python :: 3.8
Classifier: Programming Language :: Python :: 3.9
Classifier: Programming Language :: Python :: 3.10
Classifier: Programming Language :: Python :: 3.11
Classifier: Programming Language :: Python :: 3.12
Requires-Python: >=3.8
Requires-Dist: msgpack>=1.0.0
